dbnd/__init__.py
dbnd/__main__.py
dbnd/errors.py
dbnd/_core/__init__.py
dbnd/_core/access.py
dbnd/_core/constants.py
dbnd/_core/current.py
dbnd/_core/failures.py
dbnd/_core/cli/__init__.py
dbnd/_core/cli/click_utils.py
dbnd/_core/cli/cmd_deprecated.py
dbnd/_core/cli/cmd_show.py
dbnd/_core/cli/cmd_tracker.py
dbnd/_core/cli/main.py
dbnd/_core/configuration/__init__.py
dbnd/_core/configuration/config_path.py
dbnd/_core/configuration/config_readers.py
dbnd/_core/configuration/config_store.py
dbnd/_core/configuration/config_value.py
dbnd/_core/configuration/dbnd_config.py
dbnd/_core/configuration/environ_config.py
dbnd/_core/configuration/environ_dbnd_home.py
dbnd/_core/configuration/pprint_config.py
dbnd/_core/configuration/project_env.py
dbnd/_core/context/__init__.py
dbnd/_core/context/bootstrap.py
dbnd/_core/context/databand_context.py
dbnd/_core/context/use_dbnd_airflow_tracking.py
dbnd/_core/context/use_dbnd_run.py
dbnd/_core/errors/__init__.py
dbnd/_core/errors/base.py
dbnd/_core/errors/errors_utils.py
dbnd/_core/errors/show_error_once.py
dbnd/_core/errors/friendly_error/__init__.py
dbnd/_core/errors/friendly_error/api.py
dbnd/_core/errors/friendly_error/config.py
dbnd/_core/errors/friendly_error/helpers.py
dbnd/_core/errors/friendly_error/targets.py
dbnd/_core/errors/friendly_error/task_build.py
dbnd/_core/errors/friendly_error/task_parameters.py
dbnd/_core/errors/friendly_error/task_registry.py
dbnd/_core/errors/friendly_error/tools.py
dbnd/_core/log/__init__.py
dbnd/_core/log/buffered_log_manager.py
dbnd/_core/log/buffered_memory_handler.py
dbnd/_core/log/config.py
dbnd/_core/log/dbnd_log.py
dbnd/_core/log/external_exception_logging.py
dbnd/_core/log/log_preview.py
dbnd/_core/log/logging_utils.py
dbnd/_core/log/spark_debug_log.py
dbnd/_core/parameter/__init__.py
dbnd/_core/parameter/constants.py
dbnd/_core/parameter/parameter_builder.py
dbnd/_core/parameter/parameter_builder.pyi
dbnd/_core/parameter/parameter_config.py
dbnd-1.0.30.1.dist-info/LICENSE
dbnd-1.0.30.1.dist-info/METADATA
dbnd-1.0.30.1.dist-info/WHEEL
dbnd-1.0.30.1.dist-info/entry_points.txt
dbnd-1.0.30.1.dist-info/top_level.txt
dbnd-1.0.30.1.dist-info/RECORD
