Metadata-Version: 2.1
Name: dbnd
Version: 1.0.30.1
Summary: Machine Learning Orchestration
Home-page: https://github.com/databand-ai/dbnd
Author: Evgeny Shulman
Author-email: evgeny.shulman@databand.ai
Maintainer: Evgeny Shulman
Maintainer-email: evgeny.shulman@databand.ai
Project-URL: Documentation, https://dbnd.readme.io/
Project-URL: Bug-Tracker, https://github.com/databand-ai/dbnd/issues
Project-URL: Source-Code, https://github.com/databand-ai/dbnd
Keywords: orchestration,data,machinelearning
Platform: any
Classifier: Development Status :: 4 - Beta
Classifier: Intended Audience :: Developers
Classifier: Natural Language :: English
Classifier: License :: OSI Approved :: Apache Software License
Classifier: Operating System :: OS Independent
Classifier: Programming Language :: Python
Classifier: Programming Language :: Python :: 3
Classifier: Programming Language :: Python :: 3.7
Classifier: Programming Language :: Python :: 3.8
Classifier: Programming Language :: Python :: 3.9
Classifier: Programming Language :: Python :: 3.10
Classifier: Programming Language :: Python :: 3.11
Classifier: Programming Language :: Python :: Implementation :: CPython
Classifier: Programming Language :: Python :: Implementation :: PyPy
Classifier: Topic :: Software Development :: Libraries :: Python Modules
Requires-Python: >=3.6, <3.14
License-File: LICENSE
Requires-Dist: tzlocal
Requires-Dist: six
Requires-Dist: more-itertools
Requires-Dist: attrs (!=21.1.0)
Requires-Dist: pyyaml
Requires-Dist: pytz
Requires-Dist: pytzdata
Requires-Dist: requests (>=2.18.0)
Requires-Dist: pygments (>=2.6.1)
Requires-Dist: python-dateutil
Requires-Dist: sqlparse
Requires-Dist: jinja2
Requires-Dist: configparser (<3.6.0,>=3.5.0) ; python_version < "3.10"
Requires-Dist: typing ; python_version < "3.7"
Requires-Dist: colorama ; sys_platform=="win32"
Provides-Extra: jupyter
Requires-Dist: qtconsole (==4.7.7) ; extra == 'jupyter'
Requires-Dist: nbconvert ; extra == 'jupyter'
Requires-Dist: nbformat ; extra == 'jupyter'
Requires-Dist: jupyter ; extra == 'jupyter'
Requires-Dist: traitlets (<5.0.0,>=4.2) ; extra == 'jupyter'
Requires-Dist: IPython ; extra == 'jupyter'
Requires-Dist: jupyter-contrib-nbextensions ; extra == 'jupyter'
Provides-Extra: test-jupyter
Requires-Dist: nbconvert (>=7.16.4) ; extra == 'test-jupyter'
Requires-Dist: nbformat ; extra == 'test-jupyter'
Requires-Dist: jupyter ; extra == 'test-jupyter'
Requires-Dist: traitlets ; extra == 'test-jupyter'
Requires-Dist: ipykernel ; extra == 'test-jupyter'
Provides-Extra: test-pandas
Requires-Dist: openpyxl (==2.6.4) ; extra == 'test-pandas'
Requires-Dist: feather-format ; extra == 'test-pandas'
Requires-Dist: pyarrow ; extra == 'test-pandas'
Requires-Dist: numpy (<1.23) ; (python_version < "3.12") and extra == 'test-pandas'
Requires-Dist: pandas (<2.0.0,>=0.17.1) ; (python_version < "3.12") and extra == 'test-pandas'
Requires-Dist: tables (==3.7.0) ; (python_version < "3.12") and extra == 'test-pandas'
Requires-Dist: scikit-learn (==0.23.2) ; (python_version < "3.8") and extra == 'test-pandas'
Requires-Dist: matplotlib (==3.3.0) ; (python_version < "3.8") and extra == 'test-pandas'
Requires-Dist: numpy (>2.1.0) ; (python_version > "3.12") and extra == 'test-pandas'
Requires-Dist: pandas (>2) ; (python_version >= "3.12") and extra == 'test-pandas'
Requires-Dist: numpy (<2) ; (python_version >= "3.12" and python_version < "3.13") and extra == 'test-pandas'
Requires-Dist: scikit-learn (==1.5.0) ; (python_version >= "3.12" and python_version < "3.13") and extra == 'test-pandas'
Requires-Dist: tables (==3.9.2) ; (python_version >= "3.12" and python_version < "3.13") and extra == 'test-pandas'
Requires-Dist: scikit-learn (==1.6.0) ; (python_version >= "3.13") and extra == 'test-pandas'
Requires-Dist: matplotlib (==3.10.5) ; (python_version >= "3.13") and extra == 'test-pandas'
Requires-Dist: tables (==3.10.2) ; (python_version >= "3.13") and extra == 'test-pandas'
Requires-Dist: scikit-learn (==1.2.0) ; (python_version >= "3.8" and python_version < "3.12") and extra == 'test-pandas'
Requires-Dist: matplotlib (==3.6.2) ; (python_version >= "3.8" and python_version < "3.12") and extra == 'test-pandas'
Provides-Extra: test-spark2
Requires-Dist: pytest-spark (==0.6.0) ; extra == 'test-spark2'
Requires-Dist: pyspark (==2.4.4) ; (python_version < "3.8") and extra == 'test-spark2'
Provides-Extra: test-spark3
Requires-Dist: pytest-spark (==0.6.0) ; extra == 'test-spark3'
Requires-Dist: pyspark (==3.3.1) ; (python_version >= "3.8") and extra == 'test-spark3'
Provides-Extra: tests
Requires-Dist: coverage ; extra == 'tests'
Requires-Dist: mock ; extra == 'tests'
Requires-Dist: wheel ; extra == 'tests'
Requires-Dist: pytest-cov (==2.9.0) ; (python_version < "3.10") and extra == 'tests'
Requires-Dist: tox (==3.12.1) ; (python_version < "3.8") and extra == 'tests'
Requires-Dist: pytest (==4.5.0) ; (python_version < "3.8") and extra == 'tests'
Requires-Dist: pytest-cov (==3.0.0) ; (python_version >= "3.10") and extra == 'tests'
Requires-Dist: tox (==4.28.4) ; (python_version >= "3.8") and extra == 'tests'
Requires-Dist: pytest (==6.2.5) ; (python_version >= "3.8") and extra == 'tests'
